barkus/__init__.py
barkus/functions/__init__.py
barkus/functions/test/__init__.py
barkus/functions/test/base_suite.py
barkus/functions/test/raise_pydantic_validation_error.py
barkus/functions/test/response_assertion.py
barkus/functions/test/matchers/__init__.py
barkus/functions/test/matchers/response_matcher.py
barkus/functions/test/patcher/__init__.py
barkus/functions/test/patcher/base_patcher.py
barkus/functions/test/patcher/context.py
barkus/functions/test/patcher/type_patcher.py
barkus/functions/test/patcher/use_patcher.py
barkus_func_test-0.0.1.dist-info/LICENSE
barkus_func_test-0.0.1.dist-info/METADATA
barkus_func_test-0.0.1.dist-info/WHEEL
barkus_func_test-0.0.1.dist-info/top_level.txt
barkus_func_test-0.0.1.dist-info/RECORD
