Metadata-Version: 2.1
Name: barkus-func-test
Version: 0.0.1
Summary: Cloud Functions Testing Toolkit
Author: barkustech
Classifier: Programming Language :: Python :: 3.10
Classifier: License :: Free For Educational Use
Classifier: Operating System :: OS Independent
Requires-Python: >=3.10
License-File: LICENSE
Requires-Dist: pydantic ==1.10.7
Requires-Dist: dacite ==1.8.1
Requires-Dist: polyfactory ==2.2.0
Requires-Dist: pytest ==7.2.2
Requires-Dist: pytest-cov ==4.0.0
Requires-Dist: pytest-mock ==3.10.0
Requires-Dist: pytest-watch ==4.2.0
Requires-Dist: mock-firestore ==0.11.0
